const.py
const.store-2023.5.0.dist-info/LICENSE.txt
const.store-2023.5.0.dist-info/METADATA
const.store-2023.5.0.dist-info/WHEEL
const.store-2023.5.0.dist-info/top_level.txt
const.store-2023.5.0.dist-info/RECORD
