Metadata-Version: 2.1
Name: const.store
Version: 2023.5.0
Summary: Load const objects in Python functions
Author-email: Nicolas Tessore <n.tessore@ucl.ac.uk>
License: MIT
Project-URL: Homepage, https://github.com/ntessore/const
Project-URL: Issues, https://github.com/ntessore/const/issues
Classifier: License :: OSI Approved :: MIT License
Requires-Python: >=3.8
License-File: LICENSE.txt
